{
  "$schema": "https://raw.githubusercontent.com/hougesen/mdsf/main/schemas/v0.0.9/mdsf.schema.json",
  "format_finished_document": false,
  "javascript_runtime": "node",
  "languages": {
    "javascript": [["prettier", "biome", "deno_fmt", "clang-format"]],
    "rust": "rustfmt",
    "typescript": [["prettier", "biome", "deno_fmt"]],
    "sql": [["sql-formatter", "sqlfluff"]],
    "swift": [["swift-format", "swiftformat"]],
    "yaml": [["prettier", "yamlfmt", "yamlfix"]],
    "toml": "taplo",
    "go": [
      ["gci", "goimports-reviser", "goimports"],
      ["gofumpt", "gofmt", "crlfmt"]
    ],
    "cpp": "clang-format",
    "ruby": [["rubocop", "rufo", "rubyfmt", "standardrb"]],
    "zig": "zigfmt",
    "java": [["google-java-format", "clang-format"]],
    "c": "clang-format",
    "haskell": [["fourmolu", "ormolu", "hindent", "stylish-haskell"]]
  }
}
