{
  "$schema": "../tool.schema.json",
  "binary": "purty",
  "categories": ["formatter"],
  "commands": {
    "": {
      "arguments": ["--write", "$PATH"],
      "tests": [
        {
          "language": "purescript",
          "test_input": "module Mdsf where\n\n\n\n\nadd   :: Int -> Int  ->    Int\nadd a   b = a +         b\n",
          "test_output": "module Mdsf where\n\nadd :: Int -> Int -> Int\nadd a b = a + b\n"
        }
      ]
    }
  },
  "description": "PureScript pretty-printer",
  "homepage": "https://gitlab.com/joneshf/purty",
  "languages": ["purescript"],
  "packages": {
    "npm": {
      "package": "purty"
    }
  }
}
